test
karait
