Metadata-Version: 1.0
Name: karait
Version: 0.0.6
Summary: A ridiculously simple cross-language queuing system, built on top of MongoDB.
Home-page: http://github.com/bcoe/karait
Author: Benjamin Coe
Author-email: bencoe@gmail.com
License: UNKNOWN
Platform: UNKNOWN
